{
    "type": "FeatureCollection",
    "features": [
        {
            "type": "Feature",
            "properties": {
                "name": "D'AMICO SERAFINA",
                "id": "13718",
                "amenity": "fuel",
                "operator": "D'AMICO SERAFINA"
            },
            "geometry": {
                "type": "Point",
                "coordinates": [
                    14.221304454259553,
                    40.556237478427484
                ]
            }
        },
        {
            "type": "Feature",
            "properties": {
                "name": "8105",
                "id": "12163",
                "brand": "Agip Eni",
                "amenity": "fuel",
                "operator": "PETROLDOMO E AFFINI S.R.L."
            },
            "geometry": {
                "type": "Point",
                "coordinates": [
                    14.237217058996634,
                    40.54988166500174
                ]
            }
        }
    ]
}